dataproxy/__init__.py
dataproxy/_lib.so
dataproxy/file_adapter.py
dataproxy/protos.py
dataproxy/stream.py
secretflow_dataproxy-0.5.0.dev20250416.dist-info/WHEEL
secretflow_dataproxy-0.5.0.dev20250416.dist-info/METADATA
secretflow_dataproxy-0.5.0.dev20250416.dist-info/RECORD
